_itkpix_efuse_codec.cpython-39-x86_64-linux-gnu.so
cli/codec_cli.py
cli/__init__.py
cli/cli.py
itkpix_efuse_codec/__init__.py
itkpix_efuse_codec/_itkpix_efuse_codec.cpython-39-x86_64-linux-gnu.so
itkpix_efuse_codec-0.3.3.dist-info/entry_points.txt
itkpix_efuse_codec-0.3.3.dist-info/LICENSE
itkpix_efuse_codec-0.3.3.dist-info/RECORD
itkpix_efuse_codec-0.3.3.dist-info/WHEEL
itkpix_efuse_codec-0.3.3.dist-info/top_level.txt
itkpix_efuse_codec-0.3.3.dist-info/METADATA
itkpix_efuse_codec-0.3.3.data/data/requirements.txt
itkpix_efuse_codec-0.3.3.data/data/LICENSE
itkpix_efuse_codec-0.3.3.data/data/pyproject.toml
itkpix_efuse_codec-0.3.3.data/data/CMakeLists.txt
itkpix_efuse_codec-0.3.3.data/data/README.md
itkpix_efuse_codec-0.3.3.data/data/exts/hamming-codec/.pre-commit-config.yaml
itkpix_efuse_codec-0.3.3.data/data/exts/hamming-codec/.flake8
itkpix_efuse_codec-0.3.3.data/data/exts/hamming-codec/setup.py
itkpix_efuse_codec-0.3.3.data/data/exts/hamming-codec/requirements.txt
itkpix_efuse_codec-0.3.3.data/data/exts/hamming-codec/LICENSE
itkpix_efuse_codec-0.3.3.data/data/exts/hamming-codec/pyproject.toml
itkpix_efuse_codec-0.3.3.data/data/exts/hamming-codec/.git
itkpix_efuse_codec-0.3.3.data/data/exts/hamming-codec/CMakeLists.txt
itkpix_efuse_codec-0.3.3.data/data/exts/hamming-codec/MANIFEST.in
itkpix_efuse_codec-0.3.3.data/data/exts/hamming-codec/README.md
itkpix_efuse_codec-0.3.3.data/data/exts/hamming-codec/.bumpversion.cfg
itkpix_efuse_codec-0.3.3.data/data/exts/hamming-codec/.gitmodules
itkpix_efuse_codec-0.3.3.data/data/exts/hamming-codec/.gitignore
itkpix_efuse_codec-0.3.3.data/data/exts/hamming-codec/src/CMakeLists.txt
itkpix_efuse_codec-0.3.3.data/data/exts/hamming-codec/src/python/CMakeLists.txt
itkpix_efuse_codec-0.3.3.data/data/exts/hamming-codec/src/python/__init__.py
itkpix_efuse_codec-0.3.3.data/data/exts/hamming-codec/src/python/module.cpp
itkpix_efuse_codec-0.3.3.data/data/exts/hamming-codec/src/python/hamming_codec/__init__.py
itkpix_efuse_codec-0.3.3.data/data/exts/hamming-codec/src/python/cli/codec_cli.py
itkpix_efuse_codec-0.3.3.data/data/exts/hamming-codec/src/python/cli/__init__.py
itkpix_efuse_codec-0.3.3.data/data/exts/hamming-codec/src/python/cli/cli.py
