Metadata-Version: 2.1
Name: itkpix-efuse-codec
Version: 0.3.3
Summary: Utilities for encoding and decoding the data stored in the ITkPix ASIC e-fuses
Home-page: https://gitlab.cern.ch/berkeleylab/itkpix-efuse-codec
Author: Daniel Joseph Antrim
Author-email: dantrim1023@gmail.com
License: MIT
Platform: UNKNOWN
Classifier: License :: OSI Approved :: MIT License
Classifier: Programming Language :: Python :: 3
Classifier: Programming Language :: Python :: 3.8
Requires-Python: >=3.6
License-File: LICENSE
Requires-Dist: click (>=7.1.2)
